[
  {
    "id": 1,
    "name": "Oil Change",
    "image": "",
    "clicked": false
  },
  {
    "id": 2,
    "name": "Air Filter",
    "image": "./images/airFilter.png"
  },
  {
    "id": 3,
    "name": "Tune Up",
    "image": "./images/tuneUp.svg"
  },
  {
    "id": 4,
    "name": "Shocks and Struts",
    "image": "./images/shocks.svg"
  },
  {
    "id": 5,
    "name": "Brakes",
    "image": "./images/brakes.svg"
  },
  {
    "id": 6,
    "name": "Battery",
    "image": "./images/battery.svg"
  },
  {
    "id": 7,
    "name": "Coolant",
    "image": "./images/coolant.svg"
  },
  {
    "id": 8,
    "name": "Timing Belt",
    "image": "./images/timingBelt.png"
  },
  {
    "id": 9,
    "name": "Transmission",
    "image": "./images/transmission.svg"
  },
  {
    "id": 10,
    "name": "Spark Plugs",
    "image": "./images/sparkPlug.svg"
  },
  {
    "id": 11,
    "name": "Power Steering",
    "image": "./images/steering.svg"
  },
  {
    "id": 12,
    "name": "Tire Rotation",
    "image": "./images/tire.svg"
  },
  {
    "id": 13,
    "name": "Air Conditioning",
    "image": "./images/airConditioning.svg"
  }
]
